{
  "en": {
    "title": "Today's Reading",
    "today": "Today",
    "day": "Day",
    "cta_teaser": "In the Bible in One Year app you can access a full history, audio devotions, progress tracking, and more.",
    "cta": "Download today",
    "image": "/assets/img/today_en.jpg"
  },
  "es": {
    "title": "Today's Reading",
    "today": "Today",
    "day": "Day",
    "cta_teaser": "In the Bible in One Year app you can access a full history, audio devotions, progress tracking, and more.",
    "cta": "Download today",
    "image": "/assets/img/today_en.jpg"
  },
  "ar": {
    "title": "Today's Reading",
    "today": "Today",
    "day": "Day",
    "cta_teaser": "In the Bible in One Year app you can access a full history, audio devotions, progress tracking, and more.",
    "cta": "Download today",
    "image": "/assets/img/today_en.jpg"
  },
  "hi": {
    "title": "Today's Reading",
    "today": "Today",
    "day": "Day",
    "cta_teaser": "In the Bible in One Year app you can access a full history, audio devotions, progress tracking, and more.",
    "cta": "Download today",
    "image": "/assets/img/today_en.jpg"
  },
  "zh": {
    "title": "Today's Reading",
    "today": "Today",
    "day": "Day",
    "cta_teaser": "In the Bible in One Year app you can access a full history, audio devotions, progress tracking, and more.",
    "cta": "Download today",
    "image": "/assets/img/today_en.jpg"
  }
}
