{
  "en": {
    "intro": "Form a daily habit of reading Scripture",
    "about": {
      "img": "/assets/img/bioy-nicky-and-pippa-gumbel.jpg",
      "cta": {
        "label": "Find out more",
        "url": "/en/about"
      },
      "outro": "Nicky & Pippa lead Holy Trinity Brompton (HTB), a church in central London. They first introduced the Bible in One Year commentary in 2011 as a daily email for their congregation members. Since then it has grown beyond that daily email to be a website, app, podcast, and more with a worldwide following.",
      "quote": "Join us as we read the Bible each day. It’s a practice that we have been doing for over 30 years and we hope it will benefit your life as much as it has ours.",
      "intro": "Bible in One Year is a practice that Nicky & Pippa Gumbel have been doing for over thirty years. Join them each day as they take you into every chapter and every verse in the Bible and let the Holy Spirit speak into your life.",
      "header": "Let Nicky and Pippa Be Your Guide"
    },
    "header": {
      "title": "Want to get to know the Bible?",
      "strapline": "We'll take you through it, step by step.",
      "cta": "Let's Go",
      "img": {
        "src": "/assets/img/bioy-lead.jpg",
        "desc": "A woman looks up from reading Bible In One Year on her phone."
      }
    },
    "editions": {
      "intro": "Bible in One Year comes in three editions, and is being translated into many languages ...",
      "classic": "Classic",
      "youth": "Youth",
      "express": "Express"
    }
  },
  "ar": {
    "intro": "Bom dia!",
    "header": {
      "title": "Title",
      "strapline": "",
      "cta": "",
      "img": {
        "src": "/assets/img/bioy-header.jpg",
        "desc": "A man looks down at his phone, while listening to Bible in One Year"
      }
    },
    "about": {
      "img": "/assets/img/bioy-nicky-and-pippa-gumbel.jpg"
    }
  },
  "de": {
    "header": {
      "title": "Bibel lesen",
      "strapline": "We'll take you through it, step by step.",
      "cta": "Los geht's",
      "img": {
        "src": "/assets/img/bioy-lead.jpg",
        "desc": "A woman looks up from reading Bible In One Year on her phone."
      }
    }
  },
  "es": {
    "intro": "Bom dia!",
    "header": {
      "title": "Start your journey",
      "strapline": "How different could your life be if you started each morning reading the Bible?",
      "cta": "Let's Go",
      "img": {
        "src": "/assets/img/bioy-header.jpg",
        "desc": "A man looks down at his phone, while listening to Bible in One Year"
      }
    },
    "about": {
      "img": "/assets/img/bioy-nicky-and-pippa-gumbel.jpg"
    },
    "editions": {
      "classic": "Clásica",
      "express": "Exprés",
      "youth": "Jóvenes",
      "intro": "Seleccione su edición"
    }
  },
  "fr": {
    "header": {
      "title": "Envie de découvrir la Bible ?",
      "strapline": "Nous vous guiderons, pas à pas.",
      "cta": "C'est parti",
      "img": {
        "src": "/assets/img/bioy-lead.jpg",
        "desc": "Une femme lève les yeux après avoir lu la Bible en 1 an sur son téléphone."
      }
    }
  },
  "hi": {
    "intro": "Hindi welcome",
    "header": {
      "title": "Start your day with the Bible in One Year",
      "strapline": "How different could your life be if you started each morning reading the Bible?",
      "cta": "Let's Go",
      "img": {
        "src": "/assets/img/bioy-header.jpg",
        "desc": "A man looks down at his phone, while listening to Bible in One Year"
      }
    },
    "about": {
      "img": "/assets/img/bioy-nicky-and-pippa-gumbel.jpg"
    }
  },
  "th": {
    "header": {
      "title": "ต้องการทำความรู้จักกับพระคัมภีร์หรือไม่?",
      "strapline": "เราจะพาคุณไปทีละขั้นตอน",
      "cta": "เริ่มเลย",
      "img": {
        "src": "/assets/img/bioy-lead.jpg"
      }
    }
  },
  "zh": {
    "intro": "Bom dia!",
    "header": {
      "title": "以圣经日日行          开启新的一天",
      "strapline": "如果以阅读圣经来开启每一天         你的生命将大有不同！",
      "cta": "今天就开始吧",
      "img": {
        "src": "/assets/img/bioy-header.jpg",
        "desc": "A man looks down at his phone, while listening to Bible in One Year"
      }
    },
    "about": {
      "img": "/assets/img/bioy-nicky-and-pippa-gumbel.jpg"
    }
  }
}